correlated_noise_mechanism/__init__.py
correlated_noise_mechanism/blt_optimizer.py
correlated_noise_mechanism/blt_optimizer_diffloss.py
correlated_noise_mechanism/privacy_engine.py
correlated_noise_mechanism/utils.py
correlated_noise_mechanism/optimizers/__init__.py
correlated_noise_mechanism/optimizers/optimizer.py
correlated_noise_mechanism-0.3.0.dist-info/METADATA
correlated_noise_mechanism-0.3.0.dist-info/WHEEL
correlated_noise_mechanism-0.3.0.dist-info/top_level.txt
correlated_noise_mechanism-0.3.0.dist-info/RECORD
