Metadata-Version: 2.4
Name: correlated_noise_mechanism
Version: 0.3.0
Summary: Implementation of correlated noise mechanism with streaming and multi epoch settings to enable differentially private deep learning
Home-page: https://github.com/grim-hitman0XX/correlated_noise_mechanism
Author: Ashish Srivastava
Author-email: ashish.srivastava1919@gmail.com
Classifier: Programming Language :: Python :: 3
Classifier: License :: OSI Approved :: MIT License
Classifier: Operating System :: OS Independent
Requires-Python: >=3.7
Requires-Dist: numpy>=1.26.4
Requires-Dist: torch>=2.3.0
Requires-Dist: torchvision>=0.18.0
Requires-Dist: opacus>=1.5.2
Dynamic: author
Dynamic: author-email
Dynamic: classifier
Dynamic: description
Dynamic: description-content-type
Dynamic: home-page
Dynamic: requires-dist
Dynamic: requires-python
Dynamic: summary
